{
  "string": [
    {
      "name": "module_desc",
      "value": "module description"
    },
    {
      "name": "EntryAbility_desc",
      "value": "description"
    },
    {
      "name": "EntryAbility_label",
      "value": "Share"
    },
    {
      "name": "share_button",
      "value": "分享"
    },
    {
      "name": "toShare",
      "value": "分享到"
    },
    {
      "name": "cancel",
      "value": "取消"
    },
    {
      "name": "UiExtension",
      "value": "分享文本"
    },
    {
      "name": "ability_fail",
      "value": "分享Demo启动失败！"
    },
    {
      "name": "share_edit",
      "value": "分享编辑"
    },
    {
      "name": "receiver_fail",
      "value": "分享receiver启动失败！"
    }
  ]
}