{
  "app": {
    "signingConfigs": [
      {
        "name": "default",
        "material": {
          "certpath": ".\\signconfig\\auto_ohos_default_ToyVpn_com.example.testvpnclient.cer",
          "storePassword": "0000001B8FFD9FE4D98B92D5E75E097276BDFCDB18C3C255F4374E7CF9E31CA120DFDA0FCD6FA7E19F1340",
          "keyAlias": "debugKey",
          "keyPassword": "0000001B0C04F8ED18985D7621FD3964436E238EAE65A7ED815D32A3EE58627C7F9E815BD9F6F84BCAD3E2",
          "profile": ".\\signconfig\\auto_ohos_default_ToyVpn_com.example.testvpnclient.p7b",
          "signAlg": "SHA256withECDSA",
          "storeFile": ".\\signconfig\\auto_ohos_default_ToyVpn_com.example.testvpnclient.p12"
        }
      }
    ],
    "products": [
      {
        "name": "default",
        "signingConfig": "default",
        "compileSdkVersion": 10,      //指定OpenHarmony应用/服务编译时的版本
        "compatibleSdkVersion": 10,   //指定OpenHarmony应用/服务兼容的最低版本。
        "targetSdkVersion": 10,       //指定OpenHarmony应用/服务目标版本。若没有设置，默认为compatibleSdkVersion
        "runtimeOS": "OpenHarmony",   //指定为OpenHarmony
      }
    ],
    "buildModeSet": [
      {
        "name": "debug",
      },
      {
        "name": "release"
      }
    ]
  },
  "modules": [
    {
      "name": "entry",
      "srcPath": "./entry",
      "targets": [
        {
          "name": "default",
          "applyToProducts": [
            "default"
          ]
        }
      ]
    }
  ]
}